{
  "sunCredits" : 825,
  "plantDeck" : [
    6,
    7,
    0,
    9,
    4,
    8
  ],
  "suns" : [
    {
      "coordX" : 250,
      "coordY" : 108,
      "fromSunflower" : true,
      "waiting" : true
    }
  ],
  "secondsTime" : 156,
  "peas" : [
    {
      "spawnLaneX" : 1,
      "spawnLaneY" : 4,
      "damage" : 25.0,
      "plantID" : 6,
      "coordX" : 394,
      "coordY" : 414
    },
    {
      "spawnLaneX" : 1,
      "spawnLaneY" : 0,
      "damage" : 25.0,
      "plantID" : 6,
      "coordX" : 394,
      "coordY" : 62
    }
  ],
  "plants" : [
    {
      "laneX" : 0,
      "laneY" : 1,
      "startTime" : 1716551050,
      "cost" : 50,
      "range" : 0,
      "isThreaten" : false,
      "isIdle" : true,
      "cooldown" : 10.0,
      "plantHeight" : 66,
      "plantWidth" : 62,
      "jumpHeight" : 0,
      "jumpDisplacement" : 0,
      "isSquashJumped" : false,
      "isExploded" : false,
      "plantID" : 0,
      "_Health" : 100.0,
      "_is_aquatic" : false,
      "_Attack_Damage" : 0.0,
      "_Attack_Speed" : 0.0,
      "_name" : "Sunflower"
    },
    {
      "startTime" : 1716551077,
      "cost" : 200,
      "range" : -1,
      "isThreaten" : false,
      "isIdle" : true,
      "cooldown" : 10.0,
      "plantHeight" : 66,
      "plantWidth" : 62,
      "jumpHeight" : 0,
      "jumpDisplacement" : 0,
      "isSquashJumped" : false,
      "isExploded" : false,
      "laneX" : 1,
      "plantID" : 6,
      "laneY" : 1,
      "_Health" : 100.0,
      "_is_aquatic" : false,
      "_Attack_Damage" : 25.0,
      "_Attack_Speed" : 8.0,
      "_name" : "Repeater"
    },
    {
      "startTime" : 1716551094,
      "cost" : 200,
      "range" : -1,
      "isThreaten" : true,
      "isIdle" : false,
      "cooldown" : 10.0,
      "plantHeight" : 66,
      "plantWidth" : 62,
      "jumpHeight" : 0,
      "jumpDisplacement" : 0,
      "isSquashJumped" : false,
      "isExploded" : false,
      "laneX" : 1,
      "plantID" : 6,
      "laneY" : 4,
      "_Health" : 100.0,
      "_is_aquatic" : false,
      "_Attack_Damage" : 25.0,
      "_Attack_Speed" : 8.0,
      "_name" : "Repeater"
    },
    {
      "startTime" : 1716551111,
      "cost" : 200,
      "range" : -1,
      "isThreaten" : true,
      "isIdle" : false,
      "cooldown" : 10.0,
      "plantHeight" : 66,
      "plantWidth" : 62,
      "jumpHeight" : 0,
      "jumpDisplacement" : 0,
      "isSquashJumped" : false,
      "isExploded" : false,
      "laneX" : 1,
      "plantID" : 6,
      "laneY" : 0,
      "_Health" : 100.0,
      "_is_aquatic" : false,
      "_Attack_Damage" : 25.0,
      "_Attack_Speed" : 8.0,
      "_name" : "Repeater"
    }
  ],
  "isNight" : true,
  "realCooldownPlantList" : [
    0.0,
    0.0,
    0.0,
    0.0,
    0.0,
    0.0,
    0.0,
    0.0,
    0.0,
    0.0
  ],
  "zombieInMap" : 12,
  "zombieWave" : 0,
  "zombies" : [
    {
      "startTime" : 1716551197,
      "isSlowed" : false,
      "isPoleVaultingUsed" : false,
      "isDolphinJumped" : false,
      "zombieID" : 3,
      "coordX" : 992.00195,
      "laneX" : 9,
      "coordY" : 2,
      "laneY" : 0,
      "_Health" : 250.0,
      "_is_aquatic" : false,
      "_Attack_Damage" : 100.0,
      "_Attack_Speed" : 1.0,
      "_name" : "Buckethead Zombie"
    },
    {
      "startTime" : 1716551064,
      "isSlowed" : false,
      "isPoleVaultingUsed" : false,
      "isDolphinJumped" : false,
      "zombieID" : 5,
      "coordX" : 466.6164,
      "laneX" : 3,
      "coordY" : 178,
      "laneY" : 2,
      "_Health" : 175.0,
      "_is_aquatic" : true,
      "_Attack_Damage" : 100.0,
      "_Attack_Speed" : 1.0,
      "_name" : "Dolphin Rider Zombie"
    },
    {
      "startTime" : 1716551067,
      "isSlowed" : false,
      "isPoleVaultingUsed" : false,
      "isDolphinJumped" : false,
      "zombieID" : 5,
      "coordX" : 478.51712,
      "laneX" : 3,
      "coordY" : 178,
      "laneY" : 2,
      "_Health" : 175.0,
      "_is_aquatic" : true,
      "_Attack_Damage" : 100.0,
      "_Attack_Speed" : 1.0,
      "_name" : "Dolphin Rider Zombie"
    },
    {
      "startTime" : 1716551079,
      "isSlowed" : false,
      "isPoleVaultingUsed" : false,
      "isDolphinJumped" : false,
      "zombieID" : 4,
      "coordX" : 525.8158,
      "laneX" : 3,
      "coordY" : 178,
      "laneY" : 2,
      "_Health" : 100.0,
      "_is_aquatic" : true,
      "_Attack_Damage" : 100.0,
      "_Attack_Speed" : 1.0,
      "_name" : "Ducky Tube Zombie"
    },
    {
      "startTime" : 1716551109,
      "isSlowed" : false,
      "isPoleVaultingUsed" : false,
      "isDolphinJumped" : false,
      "zombieID" : 4,
      "coordX" : 645.4866,
      "laneX" : 5,
      "coordY" : 178,
      "laneY" : 2,
      "_Health" : 100.0,
      "_is_aquatic" : true,
      "_Attack_Damage" : 100.0,
      "_Attack_Speed" : 1.0,
      "_name" : "Ducky Tube Zombie"
    },
    {
      "startTime" : 1716551152,
      "isSlowed" : false,
      "isPoleVaultingUsed" : false,
      "isDolphinJumped" : false,
      "zombieID" : 5,
      "coordX" : 812.0459,
      "laneX" : 7,
      "coordY" : 178,
      "laneY" : 2,
      "_Health" : 175.0,
      "_is_aquatic" : true,
      "_Attack_Damage" : 100.0,
      "_Attack_Speed" : 1.0,
      "_name" : "Dolphin Rider Zombie"
    },
    {
      "startTime" : 1716551067,
      "isSlowed" : false,
      "isPoleVaultingUsed" : false,
      "isDolphinJumped" : false,
      "zombieID" : 5,
      "coordX" : 478.51712,
      "laneX" : 3,
      "coordY" : 266,
      "laneY" : 3,
      "_Health" : 175.0,
      "_is_aquatic" : true,
      "_Attack_Damage" : 100.0,
      "_Attack_Speed" : 1.0,
      "_name" : "Dolphin Rider Zombie"
    },
    {
      "startTime" : 1716551130,
      "isSlowed" : false,
      "isPoleVaultingUsed" : false,
      "isDolphinJumped" : false,
      "zombieID" : 5,
      "coordX" : 728.76624,
      "laneX" : 6,
      "coordY" : 266,
      "laneY" : 3,
      "_Health" : 175.0,
      "_is_aquatic" : true,
      "_Attack_Damage" : 100.0,
      "_Attack_Speed" : 1.0,
      "_name" : "Dolphin Rider Zombie"
    },
    {
      "startTime" : 1716551167,
      "isSlowed" : false,
      "isPoleVaultingUsed" : false,
      "isDolphinJumped" : false,
      "zombieID" : 5,
      "coordX" : 872.3312,
      "laneX" : 8,
      "coordY" : 266,
      "laneY" : 3,
      "_Health" : 175.0,
      "_is_aquatic" : true,
      "_Attack_Damage" : 100.0,
      "_Attack_Speed" : 1.0,
      "_name" : "Dolphin Rider Zombie"
    },
    {
      "startTime" : 1716551197,
      "isSlowed" : false,
      "isPoleVaultingUsed" : false,
      "isDolphinJumped" : false,
      "zombieID" : 1,
      "coordX" : 992.00195,
      "laneX" : 9,
      "coordY" : 354,
      "laneY" : 4,
      "_Health" : 250.0,
      "_is_aquatic" : false,
      "_Attack_Damage" : 100.0,
      "_Attack_Speed" : 1.0,
      "_name" : "Conehead Zombie"
    },
    {
      "startTime" : 1716551130,
      "isSlowed" : false,
      "isPoleVaultingUsed" : false,
      "isDolphinJumped" : false,
      "zombieID" : 3,
      "coordX" : 728.76624,
      "laneX" : 6,
      "coordY" : 442,
      "laneY" : 5,
      "_Health" : 175.0,
      "_is_aquatic" : false,
      "_Attack_Damage" : 100.0,
      "_Attack_Speed" : 1.0,
      "_name" : "Pole Vaulting Zombie"
    },
    {
      "startTime" : 1716551197,
      "isSlowed" : false,
      "isPoleVaultingUsed" : false,
      "isDolphinJumped" : false,
      "zombieID" : 3,
      "coordX" : 992.00195,
      "laneX" : 9,
      "coordY" : 442,
      "laneY" : 5,
      "_Health" : 300.0,
      "_is_aquatic" : false,
      "_Attack_Damage" : 100.0,
      "_Attack_Speed" : 1.0,
      "_name" : "Buckethead Zombie"
    }
  ]
}